shortlinks/.DS_Store
shortlinks/__init__.py
shortlinks/app.py
shortlinks/static/fonts/.DS_Store
shortlinks/static/fonts/IBM_Plex/.DS_Store
shortlinks/static/fonts/IBM_Plex/IBMPlexMono-Bold.ttf
shortlinks/static/fonts/IBM_Plex/IBMPlexMono-BoldItalic.ttf
shortlinks/static/fonts/IBM_Plex/IBMPlexMono-ExtraLight.ttf
shortlinks/static/fonts/IBM_Plex/IBMPlexMono-ExtraLightItalic.ttf
shortlinks/static/fonts/IBM_Plex/IBMPlexMono-Italic.ttf
shortlinks/static/fonts/IBM_Plex/IBMPlexMono-Light.ttf
shortlinks/static/fonts/IBM_Plex/IBMPlexMono-LightItalic.ttf
shortlinks/static/fonts/IBM_Plex/IBMPlexMono-Medium.ttf
shortlinks/static/fonts/IBM_Plex/IBMPlexMono-MediumItalic.ttf
shortlinks/static/fonts/IBM_Plex/IBMPlexMono-Regular.ttf
shortlinks/static/fonts/IBM_Plex/IBMPlexMono-SemiBold.ttf
shortlinks/static/fonts/IBM_Plex/IBMPlexMono-SemiBoldItalic.ttf
shortlinks/static/fonts/IBM_Plex/IBMPlexMono-Thin.ttf
shortlinks/static/fonts/IBM_Plex/IBMPlexMono-ThinItalic.ttf
shortlinks/static/fonts/IBM_Plex/IBMPlexSans-Bold.ttf
shortlinks/static/fonts/IBM_Plex/IBMPlexSans-BoldItalic.ttf
shortlinks/static/fonts/IBM_Plex/IBMPlexSans-ExtraLight.ttf
shortlinks/static/fonts/IBM_Plex/IBMPlexSans-ExtraLightItalic.ttf
shortlinks/static/fonts/IBM_Plex/IBMPlexSans-Italic.ttf
shortlinks/static/fonts/IBM_Plex/IBMPlexSans-Light.ttf
shortlinks/static/fonts/IBM_Plex/IBMPlexSans-LightItalic.ttf
shortlinks/static/fonts/IBM_Plex/IBMPlexSans-Medium.ttf
shortlinks/static/fonts/IBM_Plex/IBMPlexSans-MediumItalic.ttf
shortlinks/static/fonts/IBM_Plex/IBMPlexSans-Regular.ttf
shortlinks/static/fonts/IBM_Plex/IBMPlexSans-SemiBold.ttf
shortlinks/static/fonts/IBM_Plex/IBMPlexSans-SemiBoldItalic.ttf
shortlinks/static/fonts/IBM_Plex/IBMPlexSans-Thin.ttf
shortlinks/static/fonts/IBM_Plex/IBMPlexSans-ThinItalic.ttf
shortlinks/static/fonts/IBM_Plex/IBMPlexSerif-Bold.ttf
shortlinks/static/fonts/IBM_Plex/IBMPlexSerif-BoldItalic.ttf
shortlinks/static/fonts/IBM_Plex/IBMPlexSerif-ExtraLight.ttf
shortlinks-0.1.1.dist-info/METADATA
shortlinks-0.1.1.dist-info/WHEEL
shortlinks-0.1.1.dist-info/entry_points.txt
shortlinks-0.1.1.dist-info/RECORD
